wtforms/__init__.py
wtforms/form.py
wtforms/i18n.py
wtforms/meta.py
wtforms/utils.py
wtforms/validators.py
wtforms/csrf/__init__.py
wtforms/csrf/core.py
wtforms/csrf/session.py
wtforms/fields/__init__.py
wtforms/fields/choices.py
wtforms/fields/core.py
wtforms/fields/datetime.py
wtforms/fields/form.py
wtforms/fields/list.py
wtforms/fields/numeric.py
wtforms/fields/simple.py
wtforms/locale/README.md
wtforms/locale/wtforms.pot
wtforms/locale/ar/LC_MESSAGES/wtforms.mo
wtforms/locale/ar/LC_MESSAGES/wtforms.po
wtforms/locale/bg/LC_MESSAGES/wtforms.mo
wtforms/locale/bg/LC_MESSAGES/wtforms.po
wtforms/locale/ca/LC_MESSAGES/wtforms.mo
wtforms/locale/ca/LC_MESSAGES/wtforms.po
wtforms/locale/cs_CZ/LC_MESSAGES/wtforms.mo
wtforms/locale/cs_CZ/LC_MESSAGES/wtforms.po
wtforms/locale/cy/LC_MESSAGES/wtforms.mo
wtforms/locale/cy/LC_MESSAGES/wtforms.po
wtforms/locale/de/LC_MESSAGES/wtforms.mo
wtforms/locale/de/LC_MESSAGES/wtforms.po
wtforms/locale/de_CH/LC_MESSAGES/wtforms.mo
wtforms/locale/de_CH/LC_MESSAGES/wtforms.po
wtforms/locale/el/LC_MESSAGES/wtforms.mo
wtforms/locale/el/LC_MESSAGES/wtforms.po
wtforms/locale/en/LC_MESSAGES/wtforms.mo
wtforms/locale/en/LC_MESSAGES/wtforms.po
wtforms/locale/es/LC_MESSAGES/wtforms.mo
wtforms/locale/es/LC_MESSAGES/wtforms.po
wtforms/locale/et/LC_MESSAGES/wtforms.mo
wtforms/locale/et/LC_MESSAGES/wtforms.po
wtforms/locale/fa/LC_MESSAGES/wtforms.mo
wtforms/locale/fa/LC_MESSAGES/wtforms.po
wtforms/locale/fi/LC_MESSAGES/wtforms.mo
wtforms/locale/fi/LC_MESSAGES/wtforms.po
wtforms/locale/fr/LC_MESSAGES/wtforms.mo
wtforms/locale/fr/LC_MESSAGES/wtforms.po
wtforms/locale/he/LC_MESSAGES/wtforms.mo
wtforms/locale/he/LC_MESSAGES/wtforms.po
wtforms/locale/hu/LC_MESSAGES/wtforms.mo
wtforms/locale/hu/LC_MESSAGES/wtforms.po
wtforms/locale/it/LC_MESSAGES/wtforms.mo
wtforms/locale/it/LC_MESSAGES/wtforms.po
wtforms/locale/ja/LC_MESSAGES/wtforms.mo
wtforms/locale/ja/LC_MESSAGES/wtforms.po
wtforms/locale/ko/LC_MESSAGES/wtforms.mo
wtforms/locale/ko/LC_MESSAGES/wtforms.po
WTForms-3.0.0.dist-info/LICENSE.rst
WTForms-3.0.0.dist-info/METADATA
WTForms-3.0.0.dist-info/WHEEL
WTForms-3.0.0.dist-info/top_level.txt
WTForms-3.0.0.dist-info/RECORD
