Metadata-Version: 2.1
Name: WTForms
Version: 3.0.0
Summary: Form validation and rendering for Python web development.
Home-page: https://wtforms.readthedocs.io/
Maintainer: WTForms
Maintainer-email: davidism@gmail.com
License: BSD-3-Clause
Project-URL: Documentation, https://wtforms.readthedocs.io/
Project-URL: Code, https://github.com/wtforms/wtforms
Project-URL: Issue Tracker, https://github.com/wtforms/wtforms/issues
Platform: UNKNOWN
Classifier: Development Status :: 5 - Production/Stable
Classifier: Environment :: Web Environment
Classifier: Intended Audience :: Developers
Classifier: License :: OSI Approved :: BSD License
Classifier: Operating System :: OS Independent
Classifier: Programming Language :: Python
Classifier: Topic :: Internet :: WWW/HTTP :: Dynamic Content
Requires-Python: >=3.6
Provides-Extra: email
License-File: LICENSE.rst
